MANIFEST.in
README.rst
setup.py
docs/HISTORY.txt
docs/INSTALL.txt
docs/LICENSE.GPL
docs/LICENSE.txt
ftw/__init__.py
ftw.contenttemplates.egg-info/PKG-INFO
ftw.contenttemplates.egg-info/SOURCES.txt
ftw.contenttemplates.egg-info/dependency_links.txt
ftw.contenttemplates.egg-info/entry_points.txt
ftw.contenttemplates.egg-info/namespace_packages.txt
ftw.contenttemplates.egg-info/not-zip-safe
ftw.contenttemplates.egg-info/requires.txt
ftw.contenttemplates.egg-info/top_level.txt
ftw/contenttemplates/__init__.py
ftw/contenttemplates/configure.zcml
ftw/contenttemplates/factory.py
ftw/contenttemplates/interfaces.py
ftw/contenttemplates/migration.py
ftw/contenttemplates/testing.py
ftw/contenttemplates/browser/__init__.py
ftw/contenttemplates/browser/configure.zcml
ftw/contenttemplates/browser/create_from_template.pt
ftw/contenttemplates/browser/create_from_template.py
ftw/contenttemplates/locales/ftw.contenttemplates.pot
ftw/contenttemplates/locales/plone.pot
ftw/contenttemplates/locales/de/LC_MESSAGES/ftw.contenttemplates.po
ftw/contenttemplates/locales/de/LC_MESSAGES/plone.po
ftw/contenttemplates/locales/nl/LC_MESSAGES/ftw.contenttemplates.po
ftw/contenttemplates/locales/nl/LC_MESSAGES/plone.po
ftw/contenttemplates/profiles/default/metadata.xml
ftw/contenttemplates/profiles/default/registry.xml
ftw/contenttemplates/profiles/default/types/Folder.xml
ftw/contenttemplates/profiles/default/types/Plone_Site.xml
ftw/contenttemplates/tests/__init__.py
ftw/contenttemplates/tests/test_creation_form.py
ftw/contenttemplates/tests/test_default_template_factory.py