Metadata-Version: 1.1
Name: ftw.contenttemplates
Version: 1.2.1
Summary: Create content objects from templates.
Home-page: https://github.com/4teamwork/ftw.contenttemplates
Author: 4teamwork GmbH
Author-email: mailto:info@4teamwork.ch
License: GPL2
Keywords: plone ftw content templates
Platform: UNKNOWN
Classifier: Framework :: Plone
Classifier: Framework :: Plone :: 4.1
Classifier: Framework :: Plone :: 4.2
Classifier: Framework :: Plone :: 4.3
Classifier: Programming Language :: Python
Classifier: Topic :: Software Development :: Libraries :: Python Modules
